lp_ap_tools/__init__.py
lp_ap_tools/lp_ap_tools.py
tests/__init__.py
tests/lp_ap_tools_test.py
lp_ap_tools-0.1.3.dist-info/METADATA
lp_ap_tools-0.1.3.dist-info/WHEEL
lp_ap_tools-0.1.3.dist-info/top_level.txt
lp_ap_tools-0.1.3.dist-info/RECORD
